{
    "pools": [
        {
            "rolls": {
                "min": 4,
                "max": 8
            },
            "entries": [
                {
                    "type": "item",
                    "weight": 5,
                    "name": "minecraft:ender_eye"
                },
                {
                    "type": "item",
                    "weight": 20,
                    "name": "minecraft:ender_pearl"
                },
                {
                    "type": "item",
                    "weight": 25,
                    "name": "minecraft:snowball"
                },
                {
                    "type": "item",
                    "weight": 25,
                    "name": "minecraft:egg"
                },
                {
                    "type": "item",
                    "weight": 25,
                    "name": "minecraft:slime_ball"
                }
            ]
        }
    ]
}